{"Items":[{"fileNumber":1,"timeStamp":"9/15/2017 10:46:21 PM","location":"Placeholder Valley","elapsedTime":"00:04:33"},{"fileNumber":2,"timeStamp":"9/15/2017 10:41:57 PM","location":"Placeholder Valley","elapsedTime":"00:04:33"},{"fileNumber":3,"timeStamp":"9/15/2017 10:46:24 PM","location":"Placeholder Valley","elapsedTime":"00:04:33"},{"fileNumber":4,"timeStamp":"9/15/2017 10:46:16 PM","location":"Placeholder Valley","elapsedTime":"00:04:33"},{"fileNumber":5,"timeStamp":"9/15/2017 10:42:23 PM","location":"Placeholder Valley","elapsedTime":"00:04:33"},{"fileNumber":6,"timeStamp":"9/15/2017 10:43:13 PM","location":"Placeholder Valley","elapsedTime":"00:04:33"},{"fileNumber":7,"timeStamp":"9/15/2017 10:50:29 PM","location":"Placeholder Valley","elapsedTime":"00:04:33"},{"fileNumber":8,"timeStamp":"9/21/2017 10:43:53 PM","location":"Placeholder Valley","elapsedTime":"00:04:33"},{"fileNumber":9,"timeStamp":"9/26/2017 12:32:20 AM","location":"Placeholder Valley","elapsedTime":"00:04:33"},{"fileNumber":10,"timeStamp":"9/26/2017 12:35:35 AM","location":"Placeholder Valley","elapsedTime":"00:04:33"},{"fileNumber":11,"timeStamp":"9/26/2017 12:37:24 AM","location":"Placeholder Valley","elapsedTime":"00:04:33"},{"fileNumber":12,"timeStamp":"9/26/2017 12:39:35 AM","location":"Placeholder Valley","elapsedTime":"00:04:33"},{"fileNumber":13,"timeStamp":"9/26/2017 12:42:16 AM","location":"Placeholder Valley","elapsedTime":"00:04:33"}]}